keycloakfastsso/__init__.py
keycloakfastsso/decorators.py
keycloakfastsso/logging.py
keycloakfastsso/utils.py
keycloakfastsso/middleware/__init__.py
keycloakfastsso/middleware/keycloak_middleware.py
keycloak_fast_sso-2023.11.13.dist-info/LICENSE
keycloak_fast_sso-2023.11.13.dist-info/METADATA
keycloak_fast_sso-2023.11.13.dist-info/WHEEL
keycloak_fast_sso-2023.11.13.dist-info/top_level.txt
keycloak_fast_sso-2023.11.13.dist-info/RECORD
