Metadata-Version: 2.1
Name: keycloak-fast-sso
Version: 2023.11.13
Summary: FastAPI Keycloak SSO
Home-page: https://github.com/alexandre-meline/keycloakfastsso
Author: Alexandre Meline
Author-email: alexandre.meline.dev@gmail.com
License: MIT
Keywords: keycloak fastapi sso
Classifier: Programming Language :: Python :: 3
Classifier: Operating System :: OS Independent
Requires-Python: >=3.6
License-File: LICENSE
Requires-Dist: python-keycloak
Requires-Dist: fastapi
